{
  "generator-jhipster": {
    "appsFolders": ["gateway", "parking", "reservations", "payments"],
    "clusteredDbApps": [],
    "deploymentType": "kubernetes",
    "directoryPath": "../",
    "dockerPushCommand": "docker push",
    "dockerRepositoryName": "zacwastaken",
    "ingressDomain": "",
    "istio": false,
    "jwtSecretKey": "YTY5NmExMzYwNjcxMWYwYjI2YmMyMTg1Y2U4MzkxN2FmZTA2ZTEwYjlhMmNmNGM3YzYwZGFjNWIzYTQ0YWQ2YzU3MWNhNzdkMGI0NTM5N2M5Y2Y4MDkzOGJkNDk0ZjNmNGMwMQ==",
    "kubernetesNamespace": "default",
    "kubernetesServiceType": "LoadBalancer",
    "kubernetesStorageClassName": "",
    "kubernetesUseDynamicStorage": false,
    "monitoring": "no",
    "serviceDiscoveryType": "eureka"
  }
}
